cmcapi/__init__.py
cmcapi/cmc.py
cmcapi/log.py
cmcapi-0.0.3.dist-info/LICENSE
cmcapi-0.0.3.dist-info/METADATA
cmcapi-0.0.3.dist-info/WHEEL
cmcapi-0.0.3.dist-info/top_level.txt
cmcapi-0.0.3.dist-info/RECORD
