Metadata-Version: 2.1
Name: cmcapi
Version: 0.0.3
Summary: Coinmarketcap Wrapped API
Home-page: https://github.com/xueyuanl/cmcapi
Author: xueyuanl
Author-email: p.xueyuanl@gmail.com
License: UNKNOWN
Project-URL: Bug Tracker, https://github.com/xueyuanl/cmcapi/issues
Platform: UNKNOWN
Classifier: Programming Language :: Python :: 3
Classifier: License :: OSI Approved :: GNU General Public License v3 (GPLv3)
Classifier: Operating System :: OS Independent
Requires-Python: >=3.6
License-File: LICENSE
